Workbook

Sheet Balance_brute
A1: KOSSOU DISTRIBUTION — Balance générale (export brut logiciel comptable)
B2: Unité : milliers de FCFA (K FCFA) | Exercices N-1 et N
B4: N° Compte | C4: Intitulé | D4: Débit N-1 | E4: Crédit N-1 | F4: Débit N | G4: Crédit N
B5: 101000 | C5: Capital social | D5: 0 | E5: 50000 | F5: 0 | G5: 50000
B6: 106000 | C6: Reserves | D6: 0 | E6: 18000 | F6: 0 | G6: 24500
B7: 110000 | C7: Report a nouveau | D7: 0 | E7: 4200 | F7: 0 | G7: 4200
B8: 162000 | C8: Emprunts aupres des ets de credit | D8: 0 | E8: 32000 | F8: 0 | G8: 24000
B9: 213000 | C9: Logiciels | D9: 3200 | E9: 0 | F9: 4600 | G9: 0
B10: 231000 | C10: Batiments | D10: 45000 | E10: 0 | F10: 45000 | G10: 0
B11: 244000 | C11: Materiel et mobilier de bureau | D11: 12800 | E11: 0 | F11: 15200 | G11: 0
B12: 245000 | C12: Materiel de transport | D12: 21000 | E12: 0 | F12: 21000 | G12: 0
B13: 281300 | C13: Amort. logiciels | D13: 0 | E13: 1600 | F13: 0 | G13: 2400
B14: 283100 | C14: Amort. batiments | D14: 0 | E14: 9000 | F14: 0 | G14: 11250
B15: 284400 | C15: Amort. materiel et mobilier | D15: 0 | E15: 6400 | F15: 0 | G15: 8200
B16: 284500 | C16: Amort. materiel de transport | D16: 0 | E16: 8400 | F16: 0 | G16: 12600
... B42: 521000 | C42: Banque | D42: 53200 | E42: 0 | F42: 56400 | G42: 0

Sheet Nettoyage
A1: Vérification et identification des anormalies
B3: N° Compte | C3: Intitulé | D3: Débit N-1 | E3: Crédit N-1 | F3: Débit N | G3: Crédit N | H3: Solde N-1 | I3: Solde N | J3: Contrôle
B4: 101000 | C4: Capital social | D4: 0 | E4: 50000 | F4: 0 | G4: 50000 | H4: =D4-E4 -> -50000 | I4: =F4-G4 -> -50000 | J4: =$H4*$I4>0 -> TRUE
B5: 106000 | C5: Reserves | D5: 0 | E5: 18000 | F5: 0 | G5: 24500 | H5: =D5-E5 -> -18000 | I5: =F5-G5 -> -24500 | J5: =$H5*$I5>0 -> TRUE
B6: 110000 | C6: Report a nouveau | D6: 0 | E6: 4200 | F6: 0 | G6: 4200 | H6: =D6-E6 -> -4200 | I6: =F6-G6 -> -4200 | J6: =$H6*$I6>0 -> TRUE
B7: 162000 | C7: Emprunts aupres des ets de credit | D7: 0 | E7: 32000 | F7: 0 | G7: 24000 | H7: =D7-E7 -> -32000 | I7: =F7-G7 -> -24000 | J7: =$H7*$I7>0 -> TRUE
B8: 213000 | C8: Logiciels | D8: 3200 | E8: 0 | F8: 4600 | G8: 0 | H8: =D8-E8 -> 3200 | I8: =F8-G8 -> 4600 | J8: =$H8*$I8>0 -> TRUE
B9: 231000 | C9: Batiments | D9: 45000 | E9: 0 | F9: 45000 | G9: 0 | H9: =D9-E9 -> 45000 | I9: =F9-G9 -> 45000 | J9: =$H9*$I9>0 -> TRUE
B10: 244000 | C10: Materiel et mobilier de bureau | D10: 12800 | E10: 0 | F10: 15200 | G10: 0 | H10: =D10-E10 -> 12800 | I10: =F10-G10 -> 15200 | J10: =$H10*$I10>0 -> TRUE
B11: 245000 | C11: Materiel de transport | D11: 21000 | E11: 0 | F11: 21000 | G11: 0 | H11: =D11-E11 -> 21000 | I11: =F11-G11 -> 21000 | J11: =$H11*$I11>0 -> TRUE
B12: 281300 | C12: Amort. logiciels | D12: 0 | E12: 1600 | F12: 0 | G12: 2400 | H12: =D12-E12 -> -1600 | I12: =F12-G12 -> -2400 | J12: =$H12*$I12>0 -> TRUE
B13: 283100 | C13: Amort. batiments | D13: 0 | E13: 9000 | F13: 0 | G13: 11250 | H13: =D13-E13 -> -9000 | I13: =F13-G13 -> -11250 | J13: =$H13*$I13>0 -> TRUE
B14: 284400 | C14: Amort. materiel et mobilier | D14: 0 | E14: 6400 | F14: 0 | G14: 8200 | H14: =D14-E14 -> -6400 | I14: =F14-G14 -> -8200 | J14: =$H14*$I14>0 -> TRUE
B15: 284500 | C15: Amort. materiel de transport | D15: 0 | E15: 8400 | F15: 0 | G15: 12600 | H15: =D15-E15 -> -8400 | I15: =F15-G15 -> -12600 | J15: =$H15*$I15>0 -> TRUE
... B41: 521000 | C41: Banque | D41: 53200 | E41: 0 | F41: 56400 | G41: 0 | H41: =D41-E41 -> 53200 | I41: =F41-G41 -> 56400 | J41: =$H41*$I41>0 -> TRUE
C43: Total | D43: =SUM(D4:D42) -> 397450 | E43: =SUM(E4:E42) -> 397450 | F43: =SUM(F4:F42) -> 449600 | G43: =SUM(G4:G42) -> 461600 | I43: ⚠️ 3 anormalies identifiées, nettoyées et documentées : Voir dans l'onglet Anormalies
C44: Contrôle Débit = Crédit | E44: =D43-E43 -> 0 | G44: =F43-G43 -> -12000

Sheet Anormalies
A1: Journal des anormalies détectées et corrections apportées
A3: # | B3: Comptes concernés | C3: Anormies identifiées | D3: Méthode de détection | E3: Correction apportée | F3: Validé par
A4: 1 | B4: 613100 - Redevances de credit-bail | C4: En N, le compte 613100 est saisi en Crédit 6000 au lieu de Débit. Ça crée un écart de -12 000 dans le contrôle Débit=Crédit et le contrôle Nettoyage passe en FALSE | D4: PowerQuery : extraction des 3 premiers chiffres (613) et fusionné avec le Mapping. Le bucket Consommations doit être débiteur | E4: 6000 au Débit N dans la Balance nettoyée. Après correction, le solde est +6000 et le contrôle repasse à 0 | F4: -
A5: 2 | B5: 601000 - Achats de marchandises (part 2) | C5: Le compte 601000 apparaît 2 fois en N : 100800 + 67200. Le contrôle Nettoyage passe en FALSE car la 2e ligne a un débit sans contrepartie | D5: PowerQuery : extraction des 3 chiffres (601) - fusion avec le Mapping, groupement par préfixe | E5: Combinaison des 2 lignes avec SUMIF. Le solde final 601 est 168000 dans la Balance nettoyée | F5: -
A6: 3 | B6: 612000 - Entretien, reparations et maintenance | C6: En N-1, le 612000 est à 0 mais en N il y a 1450 en Débit. Le solde N-1 reste à 0, le contrôle est FALSE car la formule de report ne l'avait pas pris | D6: PowerQuery : le préfixe 612 est bien mappé en Consommations | E6: Etirement de la formule de solde pour intégrer le 1450. Le solde N final est 1450 | F6: -

Sheet Mapping
A1: Plan de mapping comptable (Balance > Compte de Résultat / Bilan)
B2: Prefixe = 3 premiers chiffres du n° de compte SYSCOHADA
B4: N° Compte | C4: Libellé de compte | D4: Bucket | E4: Position
B5: 101 | C5: Capital social | D5: Capitaux_Propres | E5: PASSIF
B6: 106 | C6: Reserves | D6: Capitaux_Propres | E6: PASSIF
B7: 110 | C7: Report a nouveau | D7: Capitaux_Propres | E7: PASSIF
B8: 162 | C8: Emprunts aupres des ets de credit | D8: Dettes_Financieres | E8: PASSIF
B9: 213 | C9: Logiciels | D9: Immo_Brut | E9: ACTIF
B10: 231 | C10: Batiments | D10: Immo_Brut | E10: ACTIF
B11: 244 | C11: Materiel et mobilier de bureau | D11: Immo_Brut | E11: ACTIF
B12: 245 | C12: Materiel de transport | D12: Immo_Brut | E12: ACTIF
B13: 2813 | C13: Amort. logiciels | D13: Amortissements | E13: ACTIF
B14: 2831 | C14: Amort. batiments | D14: Amortissements | E14: ACTIF
B15: 2844 | C15: Amort. materiel et mobilier | D15: Amortissements | E15: ACTIF
... B41: 521 | C41: Banque | D41: Tresorerie_Actif | E41: ACTIF

Sheet Balance
A1: Balance nettoyée et consolidée (formules SUMIFS sur 1.Balance_Brute)
B4: N° Compte | C4: Libellé de compte | D4: Bucket | E4: Position | F4: Solde N-1 | G4: Solde N
B5: 101 | C5: Capital social | D5: Capitaux_Propres | E5: PASSIF | F5: 50000 | G5: 50000
B6: 106 | C6: Reserves | D6: Capitaux_Propres | E6: PASSIF | F6: 18000 | G6: 24500
B7: 110 | C7: Report a nouveau | D7: Capitaux_Propres | E7: PASSIF | F7: 4200 | G7: 4200
B8: 162 | C8: Emprunts aupres des ets de credit | D8: Dettes_Financieres | E8: PASSIF | F8: 32000 | G8: 24000
B9: 213 | C9: Logiciels | D9: Immo_Brut | E9: ACTIF | F9: 3200 | G9: 4600
B10: 231 | C10: Batiments | D10: Immo_Brut | E10: ACTIF | F10: 45000 | G10: 45000
B11: 244 | C11: Materiel et mobilier de bureau | D11: Immo_Brut | E11: ACTIF | F11: 12800 | G11: 15200
B12: 245 | C12: Materiel de transport | D12: Immo_Brut | E12: ACTIF | F12: 21000 | G12: 21000
B13: 2813 | C13: Amort. logiciels | D13: Amortissements | E13: ACTIF | F13: 1600 | G13: 2400
B14: 2831 | C14: Amort. batiments | D14: Amortissements | E14: ACTIF | F14: 9000 | G14: 11250
B15: 2844 | C15: Amort. materiel et mobilier | D15: Amortissements | E15: ACTIF | F15: 6400 | G15: 8200
B16: 2845 | C16: Amort. materiel de transport | D16: Amortissements | E16: ACTIF | F16: 8400 | G16: 12600
... B42: 521 | C42: Banque | D42: Tresorerie_Actif | E42: ACTIF | F42: 53200 | G42: 56400

Sheet P&L
A1: COMPTE DE RESULTAT - SOLDES INTERMEDIAIRES DE GESTION (SIG)
B2: en milliers de FCFA - construit par formule à partir de Balance & Mapping
B4: Libellé | C4: N-1 | D4: N | E4: ecart absolu | F4: ecart en % | H4: Bucket | I4: (Tous)
B5: Chiffre_Affaires | C5: =SUMIFS(Balance[Solde N-1],Balance[Bucket], B5) -> 236000 | D5: =SUMIFS(Balance[Solde N],Balance[Bucket],B5) -> 279500 | E5: =D5-C5 -> 43500 | F5: =E5/C5 -> 0.18432203 | L5: Variation Chiffre d'affaires
B6: Achats_Marchandises | C6: =SUMIFS(Balance[Solde N-1],Balance[Bucket], B6) -> 142000 | D6: =SUMIFS(Balance[Solde N],Balance[Bucket],B6) -> 168000 | E6: =D6-C6 -> 26000 | F6: =E6/C6 -> 0.18309859 | H6: Solde.N-1 | I6: Solde.N | L6: =IF(D5=C5,"─ 0 (0,0%)",IF(C5=0,"▲ +"&TEXT(D5-C5,"# ##0")&" (N/A)",IF(D5>C5,"▲ +"&TEXT(D5-C5,"# ##0")&" ("&TEXT((D5-C5)/C5,"+0,0%")&")","▼ "&TEXT(D5-C5,"# ##0")&" ("&TEXT((D5-C5)/C5,"0,0%")&")"))) -> ▲ +43 500 (+18,4%)
B7: MARGE COMMERCIALE | C7: =C5-C6 -> 94000 | D7: =D5-D6 -> 111500 | E7: =D7-C7 -> 17500 | F7: =E7/C7 -> 0.18617021 | H7: 794900 | I7: 911200
B9: Produits_Divers | C9: =SUMIFS(Balance[Solde N-1],Balance[Bucket], B9) -> 900 | D9: =SUMIFS(Balance[Solde N],Balance[Bucket],B9) -> 1150 | E9: =D9-C9 -> 250 | F9: =E9/C9 -> 0.27777778
B10: Consommations | C10: =SUMIFS(Balance[Solde N-1],Balance[Bucket], B10) -> 25300 | D10: =SUMIFS(Balance[Solde N],Balance[Bucket],B10) -> 32650 | E10: =D10-C10 -> 7350 | F10: =E10/C10 -> 0.29051383
B11: VALEUR AJOUTEE | C11: =C7+C9-C10 -> 69600 | D11: =D7+D9-D10 -> 80000 | E11: =D11-C11 -> 10400 | F11: =E11/C11 -> 0.14942529
B13: Impots_Taxes | C13: =SUMIFS(Balance[Solde N-1],Balance[Bucket], B13) -> 1900 | D13: =SUMIFS(Balance[Solde N],Balance[Bucket],B13) -> 2200 | E13: =D13-C13 -> 300 | F13: =E13/C13 -> 0.15789474
B14: MARGE BRUTE | C14: =C11-C13 -> 67700 | D14: =D11-D13 -> 77800 | E14: =D14-C14 -> 10100 | F14: =E14/C14 -> 0.14918759
B16: Charges_Personnel | C16: =SUMIFS(Balance[Solde N-1],Balance[Bucket], B16) -> 30700 | D16: =SUMIFS(Balance[Solde N],Balance[Bucket],B16) -> 34850 | E16: =D16-C16 -> 4150 | F16: =E16/C16 -> 0.13517915
B17: EBITDA / EBE | C17: =C14-C16 -> 37000 | D17: =D14-D16 -> 42950 | E17: =D17-C17 -> 5950 | F17: =E17/C17 -> 0.16081081
B19: Dotations aux amortissements | C19: =SUMIFS(Balance[Solde N-1],Balance[Bucket], B19) -> 7100 | D19: =SUMIFS(Balance[Solde N],Balance[Bucket],B19) -> 9050 | E19: =D19-C19 -> 1950 | F19: =E19/C19 -> 0.27464789
B20: EBIT / Résultat d'Exploitation | C20: =C17-C19 -> 29900 | D20: =D17-D19 -> 33900 | E20: =D20-C20 -> 4000 | F20: =E20/C20 -> 0.13377926
B22: Produits_Financiers | C22: =SUMIFS(Balance[Solde N-1],Balance[Bucket], B22) -> 150 | D22: =SUMIFS(Balance[Solde N],Balance[Bucket],B22) -> 200 | E22: =D22-C22 -> 50 | F22: =E22/C22 -> 0.33333333
B23: Charges_Financieres | C23: =SUMIFS(Balance[Solde N-1],Balance[Bucket], B23) -> 2900 | D23: =SUMIFS(Balance[Solde N],Balance[Bucket],B23) -> 2200 | E23: =D23-C23 -> -700 | F23: =E23/C23 -> -0.24137931
B24: RESULTAT FINANCIER | C24: =C22-C23 -> -2750 | D24: =D22-D23 -> -2000 | E24: =D24-C24 -> 750 | F24: =E24/C24 -> -0.27272727
B26: RESULTAT AVANT-IMPOT | C26: =C20+C24 -> 27150 | D26: =D20+D24 -> 31900 | E26: =D26-C26 -> 4750 | F26: =E26/C26 -> 0.17495396
B27: Impot_Resultat | C27: =SUMIFS(Balance[Solde N-1],Balance[Bucket], B27) -> 4100 | D27: =SUMIFS(Balance[Solde N],Balance[Bucket],B27) -> 5450 | E27: =D27-C27 -> 1350 | F27: =E27/C27 -> 0.32926829
B29: RESULTAT NET | C29: =C26-C27 -> 23050 | D29: =D26-D27 -> 26450 | E29: =D29-C29 -> 3400 | F29: =E29/C29 -> 0.14750542

Sheet Bilan
A1: BILAN - ACTIF / PASSIF | F1: RATIOS DE LIQUIDITE
B2: en milliers de FCFA - construit par formule à partir de Balance, Mapping et P&L
B4: ACTIF | C4: N-1 | D4: N | G4: Libellé | H4: N-1 | I4: N
B5: Immobilisations brutes | C5: =SUMIFS(Balance[Solde N-1],Balance[Bucket],"Immo_Brut") -> 82000 | D5: =SUMIFS(Balance[Solde N],Balance[Bucket],"Immo_Brut") -> 85800 | G5: Liquidité Générale
B6: [-] Amortissements | C6: =SUMIFS(Balance[Solde N-1],Balance[Bucket],"Amortissements") -> 25400 | D6: =SUMIFS(Balance[Solde N],Balance[Bucket],"Amortissements") -> 34450 | G6: Actif Circulant | H6: =C9+C10+C11 -> 101450 | I6: =D9+D10+D11 -> 115400 | L6: DSO | M6: =(D10/'P&L'!D5)*365 -> 46.490161
B7: Immobilisations nettes | C7: =C5-C6 -> 56600 | D7: =D5-D6 -> 51350 | G7: Dettes à Court Terme | H7: =C21+C22 -> 30800 | I7: =D21+D22 -> 37600 | L7: DIO | M7: =(D9/'P&L'!D6)*365 -> 48.449405
G8: Ratio de Liquidité Générale | H8: =H6/H7 -> 3.2938312 | I8: =I6/I7 -> 3.0691489 | L8: DPO | M8: =(D21/'P&L'!D6)*365 -> 58.22619
B9: Stocks | C9: =SUMIFS(Balance[Solde N-1],Balance[Bucket],"Stocks") -> 18500 | D9: =SUMIFS(Balance[Solde N],Balance[Bucket],"Stocks") -> 22300
B10: Creances Clients | C10: =SUMIFS(Balance[Solde N-1],Balance[Bucket],"Creances_Clients") -> 28900 | D10: =SUMIFS(Balance[Solde N],Balance[Bucket],"Creances_Clients") -> 35600 | G10: Liquidité Réduite | L10: Variation Trésorerie
B11: Tresorerie Actif | C11: =SUMIFS(Balance[Solde N-1],Balance[Bucket],"Tresorerie_Actif") -> 54050 | D11: =SUMIFS(Balance[Solde N],Balance[Bucket],"Tresorerie_Actif") -> 57500 | G11: Créances Clients | H11: =C10 -> 28900 | I11: =D10 -> 35600 | L11: =IF(Tableau7[[#This Row],[N]]=Tableau7[[#This Row],[N-1]],"─ 0 (0,0%)",IF(Tableau7[[#This Row],[N-1]]=0,"▲ +"&TEXT(Tableau7[[#This Row],[N]]-Tableau7[[#This Row],[N-1]],"# ##0")&" (N/A)",IF(Tableau7[[#This Row],[N]]>Tableau7[[#This Row],[N-1]],"▲ +"&TEXT(Tableau7[[#This Row],[N]]-Tableau7[[#This Row],[N-1]],"# ##0")&" ("&TEXT((Tableau7[[#This Row],[N]]-Tableau7[[#This Row],[N-1]])/Tableau7[[#This Row],[N-1]],"+0,0%")&")","▼ "&TEXT(Tableau7[[#This Row],[N]]-Tableau7[[#This Row],[N-1]],"# ##0")&" ("&TEXT((Tableau7[[#This Row],[N]]-Tableau7[[#This Row],[N-1]])/Tableau7[[#This Row],[N-1]],"0,0%")&")"))) -> ▲ +3 450 (+6,4%)
G12: Disponibiltés | H12: =C11 -> 54050 | I12: =D11 -> 57500
B13: TOTAL ACTIF | C13: =C7+SUM(C9:C11) -> 158050 | D13: =D7+SUM(D9:D11) -> 166750 | G13: Dettes à Court Terme | H13: =H7 -> 30800 | I13: =I7 -> 37600 | L13: Variation RLR
G14: Ratio de Liquidité Réduite | H14: =(H11+H12)/H13 -> 2.6931818 | I14: =(I11+I12)/I13 -> 2.4760638 | L14: =IF(Tableau15[[#This Row],[N]]=Tableau15[[#This Row],[N-1]],"─ 0 (0,0%)",IF(Tableau15[[#This Row],[N-1]]=0,"▲ +"&TEXT(Tableau15[[#This Row],[N]]-Tableau15[[#This Row],[N-1]],"0,0")&" (N/A)",IF(Tableau15[[#This Row],[N]]>Tableau15[[#This Row],[N-1]],"▲ +"&TEXT(Tableau15[[#This Row],[N]]-Tableau15[[#This Row],[N-1]],"0,0")&" ("&TEXT((Tableau15[[#This Row],[N]]-Tableau15[[#This Row],[N-1]])/Tableau15[[#This Row],[N-1]],"+0,0%")&")","▼ "&TEXT(Tableau15[[#This Row],[N]]-Tableau15[[#This Row],[N-1]],"0,0")&" ("&TEXT((Tableau15[[#This Row],[N]]-Tableau15[[#This Row],[N-1]])/Tableau15[[#This Row],[N-1]],"0,0%")&")"))) -> ▼ -0,2 (-8,1%)
B16: PASSIF | C16: N-1 | D16: N | G16: Liquidité Immédiate
B17: Capitaux_Propres | C17: =SUMIFS(Balance[Solde N-1],Balance[Bucket],"Capitaux_Propres") -> 72200 | D17: =SUMIFS(Balance[Solde N],Balance[Bucket],"Capitaux_Propres") -> 78700 | G17: Disponibilités | H17: =C11 -> 54050 | I17: =D11 -> 57500 | L17: Variation Dettes financières
B18: Résultat de l'exercice | C18: ='P&L'!C29 -> 23050 | D18: ='P&L'!D29 -> 26450 | G18: Dettes à Court Terme | H18: =H13 -> 30800 | I18: =I13 -> 37600 | L18: =IF(D19=C19,"─ 0 (0,0%)",IF(C19=0,"▲ +"&TEXT(D19-C19,"# ##0")&" (N/A)",IF(D19>C19,"▲ +"&TEXT(D19-C19,"# ##0")&" ("&TEXT((D19-C19)/C19,"+0,0%")&")","▼ "&TEXT(D19-C19,"# ##0")&" ("&TEXT((D19-C19)/C19,"0,0%")&")"))) -> ▼ -8 000 (-25,0%)
B19: Dettes_Financieres | C19: =SUMIFS(Balance[Solde N-1],Balance[Bucket],"Dettes_Financieres") -> 32000 | D19: =SUMIFS(Balance[Solde N],Balance[Bucket],"Dettes_Financieres") -> 24000 | G19: Ratio de Liquidité Immédiate | H19: =H17/H18 -> 1.7548701 | I19: =I17/I18 -> 1.5292553
B21: Dettes_Fournisseurs | C21: =SUMIFS(Balance[Solde N-1],Balance[Bucket],"Dettes_Fournisseurs") -> 21400 | D21: =SUMIFS(Balance[Solde N],Balance[Bucket],"Dettes_Fournisseurs") -> 26800
B22: Dettes_Sociales_Fiscales | C22: =SUMIFS(Balance[Solde N-1],Balance[Bucket],"Dettes_Sociales_Fiscales") -> 9400 | D22: =SUMIFS(Balance[Solde N],Balance[Bucket],"Dettes_Sociales_Fiscales") -> 10800
B24: TOTAL PASSIF | C24: =SUM(C17:C19,C21:C22) -> 158050 | D24: =SUM(D17:D19,D21:D22) -> 166750
B26: Contrôle (Actif = Passif) | C26: =C13-C24 -> 0 | D26: =D13-D24 -> 0

Sheet Retraitements
A1: Retraitements analytiques - Normalisation de l'EBE (EBITDA)
B2: Hypothèses documentées ci-dessous - sans impact sur la trésorerie réelle de l'entreprise
A4: > Retraitement 613 - Redevances de crédit-bail
B5: Ventilation de la redevance de crédit-bail (Hypothèse : 70% dotation / 30% intérêts (IFRS-like)
B6: Dotation aux amortissements (Quote-part 70%) | C6: =Balance!F30*0.7 -> 4200 | D6: =Balance!G30*0.7 -> 4200
B7: Charge financière (Quote-part 30%) | C7: =Balance!F30*0.3 -> 1800 | D7: =Balance!G30*0.3 -> 1800 | F7: > Rentabilité opérationnelle Pure
B9: Libellé | C9: N-1 | D9: N | G9: Libellé | H9: N-1 | I9: N
B10: EBITDA Brut / EBE Brut | C10: ='P&L'!C17 -> 37000 | D10: ='P&L'!D17 -> 42950 | G10: EBITDA / EBE (Ajusté) | H10: =C12 -> 43000 | I10: =D12 -> 48950 | K10: Variation Rentabilité Opérationnelle
B11: [ + ] Neutralisation Redevances crédit-bail | C11: =Balance!F30 -> 6000 | D11: =Balance!G30 -> 6000 | G11: Chiffre d'Affaires | H11: ='P&L'!C5 -> 236000 | I11: ='P&L'!D5 -> 279500 | K11: =H12 -> 0.18220339 | L11: =I12 -> 0.17513417
B12: EBITDA Normalisé / EBE Retraité | C12: =C10+C11 -> 43000 | D12: =D10+D11 -> 48950 | G12: Ratio de Rentabilité Opérationnelle | H12: =H10/H11 -> 0.18220339 | I12: =I10/I11 -> 0.17513417 | K12: =IF(Tableau18[[#This Row],[N]]=Tableau18[[#This Row],[N-1]],"─ 0 (0,0%)",IF(Tableau18[[#This Row],[N-1]]=0,"▲ +"&TEXT(Tableau18[[#This Row],[N]]-Tableau18[[#This Row],[N-1]],"0,0%")&" (N/A)",IF(Tableau18[[#This Row],[N]]>Tableau18[[#This Row],[N-1]],"▲ +"&TEXT(Tableau18[[#This Row],[N]]-Tableau18[[#This Row],[N-1]],"0,0%")&" ("&TEXT((Tableau18[[#This Row],[N]]-Tableau18[[#This Row],[N-1]])/Tableau18[[#This Row],[N-1]],"+0,0%")&")","▼ "&TEXT(Tableau18[[#This Row],[N]]-Tableau18[[#This Row],[N-1]],"0,0%")&" ("&TEXT((Tableau18[[#This Row],[N]]-Tableau18[[#This Row],[N-1]])/Tableau18[[#This Row],[N-1]],"0,0%")&")"))) -> ▼ -0,7% (-3,9%)
B14: Dotations aux amortissements ajustées | C14: ='P&L'!C19+C6 -> 11300 | D14: ='P&L'!D19+D6 -> 13250 | G14: Produits_Financiers | H14: 150 | I14: 200
B15: EBIT NET / Résultat d'Exploitation Normalisé | C15: =C12-C14 -> 31700 | D15: =D12-D14 -> 35700 | G15: Charges financières ajustées | H15: 4700 | I15: 4000
G16: RESULTAT FINANCIER RETRAITE | H16: -4550 | I16: -3800
B17: ='P&L'!B22 -> Produits_Financiers | C17: ='P&L'!C22 -> 150 | D17: ='P&L'!D22 -> 200
B18: Charges financières ajustées | C18: ='P&L'!C23+C7 -> 4700 | D18: ='P&L'!D23+D7 -> 4000 | G18: RESULTAT AVANT-IMPOT | H18: 27150 | I18: 31900
B19: RESULTAT FINANCIER RETRAITE | C19: =C17-C18 -> -4550 | D19: =D17-D18 -> -3800 | G19: Impot_Resultat | H19: 4100 | I19: 5450
B21: ='P&L'!B26 -> RESULTAT AVANT-IMPOT | C21: =C15+C19 -> 27150 | D21: =D15+D19 -> 31900 | G21: RESULTAT NET RETRAITE | H21: 23050 | I21: 26450
B22: ='P&L'!B27 -> Impot_Resultat | C22: ='P&L'!C27 -> 4100 | D22: ='P&L'!D27 -> 5450
K23: Variation Résultat Net Normalisé
B24: RESULTAT NET RETRAITE | C24: =C21-C22 -> 23050 | D24: =D21-D22 -> 26450 | K24: =Tableau9[[#This Row],[N-1]] -> 23050 | L24: =Tableau9[[#This Row],[N]] -> 26450
B26: RESULTAT NET BRUT | C26: ='P&L'!C29 -> 23050 | D26: ='P&L'!D29 -> 26450
K27: =IF(D24=C24,"─ 0 (0,0%)",IF(C24=0,"▲ +"&TEXT(D24-C24,"# ##0")&" (N/A)",IF(D24>C24,"▲ +"&TEXT(D24-C24,"# ##0")&" ("&TEXT((D24-C24)/C24,"+0,0%")&")","▼ "&TEXT(D24-C24,"# ##0")&" ("&TEXT((D24-C24)/C24,"0,0%")&")"))) -> ▲ +3 400 (+14,8%)
B28: Contrôle d'ecart : | C28: =C24-C26 -> 0 | D28: =D24-D26 -> 0
K29: Variation EBITDA Normalisé
A30: > Retraitement 622 - Remunerations d'intermediaires et personnel exterieur | F30: > Performance du Personnelle | K30: =IF(D12=C12,"─ 0 (0,0%)",IF(C12=0,"▲ +"&TEXT(D12-C12,"# ##0")&" (N/A)",IF(D12>C12,"▲ +"&TEXT(D12-C12,"# ##0")&" ("&TEXT((D12-C12)/C12,"+0,0%")&")","▼ "&TEXT(D12-C12,"# ##0")&" ("&TEXT((D12-C12)/C12,"0,0%")&")"))) -> ▲ +5 950 (+13,8%)
B32: Libellé | C32: N-1 | D32: N | G32: Libellé | H32: N-1 | I32: N
B33: Consommations Brut | C33: =SUMIFS(Balance[Solde N-1],Balance[Bucket],"Consommations") -> 25300 | D33: =SUMIFS(Balance[Solde N],Balance[Bucket],"Consommations") -> 32650 | G33: Charge du personnel (Ajustée) | H33: =C37 -> 39100 | I33: =D37 -> 47450 | K33: Variation Performance Opérationnelle
B34: Consommations Retraitées | C34: =C33-SUMIFS(Balance[Solde N-1],Balance[N° Compte],"622") -> 16900 | D34: =D33-SUMIFS(Balance[Solde N],Balance[N° Compte],"622") -> 20050 | G34: Chiffre d'Affaires | H34: ='P&L'!C5 -> 236000 | I34: ='P&L'!D5 -> 279500 | K34: =H35 -> 0.16567797 | L34: =I35 -> 0.16976744
G35: Ratio de Performance Opérationnelle | H35: =H33/H34 -> 0.16567797 | I35: =I33/I34 -> 0.16976744 | K35: =IF(Tableau20[[#This Row],[N]]=Tableau20[[#This Row],[N-1]],"─ 0 (0,0%)",IF(Tableau20[[#This Row],[N-1]]=0,"▲ +"&TEXT(Tableau20[[#This Row],[N]]-Tableau20[[#This Row],[N-1]],"0,0%")&" (N/A)",IF(Tableau20[[#This Row],[N]]>Tableau20[[#This Row],[N-1]],"▲ +"&TEXT(Tableau20[[#This Row],[N]]-Tableau20[[#This Row],[N-1]],"0,0%")&" ("&TEXT((Tableau20[[#This Row],[N]]-Tableau20[[#This Row],[N-1]])/Tableau20[[#This Row],[N-1]],"+0,0%")&")","▼ "&TEXT(Tableau20[[#This Row],[N]]-Tableau20[[#This Row],[N-1]],"0,0%")&" ("&TEXT((Tableau20[[#This Row],[N]]-Tableau20[[#This Row],[N-1]])/Tableau20[[#This Row],[N-1]],"0,0%")&")"))) -> ▲ +0,4% (+2,5%)
B36: Charge du personnel Brut | C36: =SUMIFS(Balance[Solde N-1],Balance[Bucket],"Charges_Personnel") -> 30700 | D36: =SUMIFS(Balance[Solde N],Balance[Bucket],"Charges_Personnel") -> 34850
B37: Charge du personnel Retraitée | C37: =C36+SUMIFS(Balance[Solde N-1],Balance[N° Compte],"622") -> 39100 | D37: =D36+SUMIFS(Balance[Solde N],Balance[N° Compte],"622") -> 47450

Sheet BFR
A1: BESOIN EN FONDS DE ROULEMENT (BFR)
B2: en milliers de FCFA - construit à partir du Bilan
B4: Libellé | C4: N-1 | D4: N
B5: Stocks [Inventory] | C5: =Bilan!C9 -> 18500 | D5: =Bilan!D9 -> 22300 | G5: =B7 -> Actif circulant hors trésorerie | H5: =D7 -> 57900
B6: Créances clients [AR] | C6: =Bilan!C10 -> 28900 | D6: =Bilan!D10 -> 35600 | G6: =B11 -> Passif circulant hors trésorerie | H6: =D11 -> 37600
B7: Actif circulant hors trésorerie | C7: =C5+C6 -> 47400 | D7: =D5+D6 -> 57900
B9: Dettes Fournisseurs [AP] | C9: =Bilan!C21 -> 21400 | D9: =Bilan!D21 -> 26800
B10: Dettes Sociales Fiscales | C10: =Bilan!C22 -> 9400 | D10: =Bilan!D22 -> 10800
B11: Passif circulant hors trésorerie | C11: =C9+C10 -> 30800 | D11: =D9+D10 -> 37600
B13: BFR (Actif Cir. - Passif Cir.) | C13: =C7-C11 -> 16600 | D13: =D7-D11 -> 20300 | G13: Variation du BFR
B14: Variation du BFR | D14: =D13-C13 -> 3700 | G14: =IF(D13=C13,"─ 0 (0,0%)",IF(C13=0,"▲ +"&TEXT(D13-C13,"# ##0")&" (N/A)",IF(D13>C13,"▲ +"&TEXT(D13-C13,"# ##0")&" ("&TEXT((D13-C13)/C13,"+0,0%")&")","▼ "&TEXT(D13-C13,"# ##0")&" ("&TEXT((D13-C13)/C13,"0,0%")&")"))) -> ▲ +3 700 (+22,3%)
B15: CASH GAP (BFR/CA)*365 jrs | C15: =(C13/'P&L'!C5)*365 -> 25.673729 | D15: =(D13/'P&L'!D5)*365 -> 26.509839
G16: Variation Cash Gap
G17: =IF(D15=C15,"─ 0 (0,0%)",IF(C15=0,"▲ +"&TEXT(D15-C15,"0")&" (N/A)",IF(D15>C15,"▲ +"&TEXT(D15-C15,"0")&" ("&TEXT((D15-C15)/C15,"+0,0%")&")","▼ "&TEXT(D15-C15,"0")&" ("&TEXT((D15-C15)/C15,"0,0%")&")"))) -> ▲ +1 (+3,3%)

Sheet TFT
A1: TABLEAU DE FLUX DE TRESORERIE -
B2: en milliers de FCFA - reconstruit à partir du Bilan N-1/N et du P&L N par Méthode Indirecte (Exercice N)
B4: Libellé | C4: Montant | E4: Variation Nette Trésorerie | F4: Trésorerie N-1 | G4: Trésorerie N
B5: FLUX DE TRESORERIE D'EXPLOITATION | E5: =SUM(C13+C17+C22) -> 3450 | F5: =Bilan!C11 -> 54050 | G5: =Bilan!D11 -> 57500
B6: Résultat d'exercice | C6: ='P&L'!D29 -> 26450
B7: [+] Dotations aux amortissements | C7: ='P&L'!D19 -> 9050 | E7: Contrôle de réconciliation : | F7: =E5-(G5-F5) -> 0
B8: [-] Variation du BFR | C8: =(C9+C10)-(C11+C12) -> 3700
B9: ▲ Stocks | C9: =Tableau7[[#This Row],[N]]-Tableau7[[#This Row],[N-1]] -> 3800
B10: ▲ Creances Clients | C10: =Tableau7[[#This Row],[N]]-Tableau7[[#This Row],[N-1]] -> 6700
B11: ▲ Dettes_Fournisseurs | C11: =Bilan!D21-Bilan!C21 -> 5400
B12: ▲ Dettes_Sociales_Fiscales | C12: =Bilan!D22-Bilan!C22 -> 1400
B13: FLUX NET DE TRESORERIE D'EXPLOITATION | C13: =C6+C7-C8 -> 31800
B15: FLUX DE TRESORERIE D'INVESTISSEMENT
B16: [-] Acquisition d'immobilsations (▲ Immo, Brutes) | C16: =-(Bilan!D5-Bilan!C5) -> -3800
B17: FLUX NET DE TRESORERIE D'INVESTISSEMENT | C17: =SUM(C16) -> -3800
B19: FLUX DE TRESORERIE DE FINANCEMENT
B20: [+] Dettes financières (Variation annuelle) | C20: =Bilan!D19-Bilan!C19 -> -8000
B21: [-] Distribution des dividendes (estimation) | C21: ='P&L'!C29-(Bilan!D17-Bilan!C17) -> 16550
B22: FLUX NET DE TRESORERIE DE FINANCEMENT | C22: =C20-C21 -> -24550

Sheet Dashboard
B11: Suivi de trésorerie et des indicateurs clés
B12: Indicateurs | C12: N-1 | D12: N | E12: Evolution | F12: Lecture / Commentaire
B13: Trésorerie ( Banque + Caisse) | C13: =Bilan!C11 -> 54050 | D13: =Bilan!D11 -> 57500 | E13: =Bilan!L11 -> ▲ +3 450 (+6,4%) | F13: Excellente liquidité : La hausse de trésorerie confirme la rentabilité générée par l'activité se traduit par du cash réel en banque
B14: Besoin en Fonds de Roulement | C14: =BFR!C13 -> 16600 | D14: =BFR!D13 -> 20300 | E14: =BFR!G14 -> ▲ +3 700 (+22,3%) | F14: Point de vigilance : L'activité consomme plus de ressources à court terme, nécessité d'un suivi rigoureux des encours clients et des stocks
B15: Cash Gap (Jours) | C15: =BFR!C15 -> 25.673729 | D15: =BFR!D15 -> 26.509839 | E15: =BFR!G17 -> ▲ +1 (+3,3%) | F15: Légère dégradation : Le cycle de conversion du cash s'allonge de +1 jour. Cette dérive explique directement la hausse du BFR constatée
B16: Rentabilité Opérationnelle | C16: =Retraitements!H12 -> 0.18220339 | D16: =Retraitements!I12 -> 0.17513417 | E16: =Retraitements!K12 -> ▼ -0,7% (-3,9%) | F16: Performance solide : La légère baisse de 0,7 point montre une bonne maîtrise des coûts face à la hausse du chiffre d'affaires
B17: Performance opérationnelle | C17: =Retraitements!H35 -> 0.16567797 | D17: =Retraitements!I35 -> 0.16976744 | E17: =Retraitements!K35 -> ▲ +0,4% (+2,5%) | F17: Productivité maîtrisée : Le poids des charges de personnel reste stable et l'impact du personnel extérieur est totalement absorbé par la croissance de l'activité
B18: Ratio de Liquidité Réduite | C18: =Bilan!H14 -> 2.6931818 | D18: =Bilan!I14 -> 2.4760638 | E18: =Bilan!L14 -> ▼ -0,2 (-8,1%) | F18: Structure très sécurisée. Bien qu'en léger repli, l'entreprise dispose de 2,50 € d'actifs à court terme pour chaque euro de dette immédiate (seuil d'alerte à 1,0)
B19: EBE Retraité (Hors one-offs) | C19: =Retraitements!C12 -> 43000 | D19: =Retraitements!D12 -> 48950 | E19: =Retraitements!K30 -> ▲ +5 950 (+13,8%) | F19: Forte performance du cœur de métier : Les retraitements économiques confirment la forte rentabilité structurelle de l'exploitation
B20: Résultat Net Retraité | C20: =Retraitements!C24 -> 23050 | D20: =Retraitements!D24 -> 26450 | E20: =Retraitements!K27 -> ▲ +3 400 (+14,8%) | F20: Capacité d'autofinancement en hausse : Cette performance renforce les capitaux propres et valide la rentabilité globale de l'exercice
B21: Dettes financières restantes | C21: =Bilan!C19 -> 32000 | D21: =Bilan!D19 -> 24000 | E21: =Bilan!L18 -> ▼ -8 000 (-25,0%) | F21: Désendettement stratégique : L'entreprise utilise son cash disponible pour assainir sa structure financière et rassurer les partenaires bancaires
